{"projectName":"bacon.js","metric":"AMGI","usabilityResult":{"index":0.777425616711331,"keywordsRuns":{"combine":[1,1,17],"concat":[1,4],"All":[1,1,2],"from":[1,1,2,1,1,2],"Array":[1,1,1],"Event":[2,4,1],"group":[1,2],"on":[1,4],"zip":[2,1],"As":[1,1,1],"With":[1,7,15],"merge":[1,2],"Promise":[1,2],"Callback":[2],"buffer":[3],"Time":[2],"Count":[2],"transform":[4],"flat":[15],"Map":[14],"Error":[6,1],"Latest":[4],"By":[5],"map":[6],"subscribe":[3,2],"to":[6,1,5],"with":[6],"debounce":[2],"do":[4],"End":[3,1],"end":[2,1],"Value":[2,1],"first":[2],"skip":[5],"Until":[2],"While":[2],"take":[3],"Input":[2],"unsubscribe":[1,1],"Next":[3],"is":[5],"Scheduler":[2]}}}